setup.py
sscrypto/__init__.py
sscrypto/common.py
sscrypto/encrypt.py
sscrypto.egg-info/PKG-INFO
sscrypto.egg-info/SOURCES.txt
sscrypto.egg-info/dependency_links.txt
sscrypto.egg-info/not-zip-safe
sscrypto.egg-info/top_level.txt
sscrypto/crypto/__init__.py
sscrypto/crypto/ctypes_libsodium.py
sscrypto/crypto/ctypes_openssl.py
sscrypto/crypto/openssl.py
sscrypto/crypto/rc4_md5.py
sscrypto/crypto/sodium.py
sscrypto/crypto/table.py
sscrypto/crypto/util.py